pyunlocbox/__init__.py
pyunlocbox/acceleration.py
pyunlocbox/functions.py
pyunlocbox/operators.py
pyunlocbox/solvers.py
pyunlocbox/tests/test_acceleration.py
pyunlocbox/tests/test_docstrings.py
pyunlocbox/tests/test_functions.py
pyunlocbox/tests/test_operators.py
pyunlocbox/tests/test_solvers.py
pyunlocbox-0.6.1.dist-info/licenses/LICENSE.txt
pyunlocbox-0.6.1.dist-info/METADATA
pyunlocbox-0.6.1.dist-info/WHEEL
pyunlocbox-0.6.1.dist-info/top_level.txt
pyunlocbox-0.6.1.dist-info/RECORD
