Metadata-Version: 2.4
Name: pyunlocbox
Version: 0.6.1
Summary: Convex Optimization in Python using Proximal Splitting
Author: EPFL LTS2
Maintainer: EPFL LTS2
License: BSD
Project-URL: Homepage, https://github.com/epfl-lts2/pyunlocbox
Project-URL: Documentation, https://pyunlocbox.readthedocs.io
Project-URL: Repository, https://github.com/epfl-lts2/pyunlocbox
Project-URL: Bug Tracker, https://github.com/epfl-lts2/pyunlocbox/issues
Project-URL: Download, https://pypi.org/project/pyunlocbox
Project-URL: Try It Online, https://mybinder.org/v2/gh/epfl-lts2/pyunlocbox/master?urlpath=lab/tree/examples/playground.ipynb
Keywords: convex optimization
Classifier: Development Status :: 4 - Beta
Classifier: Topic :: Scientific/Engineering
Classifier: Intended Audience :: Developers
Classifier: Intended Audience :: Education
Classifier: Intended Audience :: Science/Research
Classifier: License :: OSI Approved :: BSD License
Classifier: Operating System :: OS Independent
Classifier: Programming Language :: Python
Classifier: Programming Language :: Python :: 3
Classifier: Programming Language :: Python :: 3.8
Classifier: Programming Language :: Python :: 3.9
Classifier: Programming Language :: Python :: 3.10
Classifier: Programming Language :: Python :: 3.11
Classifier: Programming Language :: Python :: 3.12
Requires-Python: >=3.8
License-File: LICENSE.txt
Requires-Dist: numpy
Requires-Dist: pytest-cov>=5.0.0
Requires-Dist: scipy
Provides-Extra: dev
Requires-Dist: pytest>=6.0; extra == "dev"
Requires-Dist: pytest-cov; extra == "dev"
Requires-Dist: pytest-xdist; extra == "dev"
Requires-Dist: flake8; extra == "dev"
Requires-Dist: coverage; extra == "dev"
Requires-Dist: coveralls; extra == "dev"
Requires-Dist: sphinx; extra == "dev"
Requires-Dist: numpydoc; extra == "dev"
Requires-Dist: sphinxcontrib-bibtex; extra == "dev"
Requires-Dist: sphinx-rtd-theme; extra == "dev"
Requires-Dist: sphinx-copybutton; extra == "dev"
Requires-Dist: matplotlib; extra == "dev"
Requires-Dist: wheel; extra == "dev"
Requires-Dist: twine; extra == "dev"
Requires-Dist: pre-commit; extra == "dev"
Requires-Dist: black; extra == "dev"
Requires-Dist: isort; extra == "dev"
Requires-Dist: bandit[toml]; extra == "dev"
Requires-Dist: nbconvert; extra == "dev"
Requires-Dist: jupyter; extra == "dev"
Dynamic: license-file
